bocfx/__init__.py
bocfx/__main__.py
bocfx-0.8.1.dist-info/LICENSE
bocfx-0.8.1.dist-info/METADATA
bocfx-0.8.1.dist-info/WHEEL
bocfx-0.8.1.dist-info/entry_points.txt
bocfx-0.8.1.dist-info/top_level.txt
bocfx-0.8.1.dist-info/RECORD
