Metadata-Version: 2.1
Name: bocfx
Version: 0.8.1
Summary: Easy API to get foreign exchange rate from Bank of China.
Home-page: https://github.com/bobleer/bocfx
Author: bobleer
Author-email: liwenbo628@gmail.com
Classifier: Programming Language :: Python :: 3
Classifier: License :: OSI Approved :: MIT License
Classifier: Operating System :: OS Independent
License-File: LICENSE
Requires-Dist: requests
Requires-Dist: scrapy
Requires-Dist: tqdm
Requires-Dist: prettytable
Requires-Dist: numpy
Requires-Dist: matplotlib
